Metadata-Version: 2.1
Name: codigofacilito
Version: 0.0.3
Summary: Permite consumir el API de CódigoFacilito
Home-page: https://github.com/Ange1D/codigofacilito_package/
Author: Ange1D
Author-email: ange1d.contact0@gmail.com
License: MIT
Keywords: codigofacilito
Platform: UNKNOWN
Classifier: Development Status :: 3 - Alpha
Classifier: Intended Audience :: Developers
Classifier: Topic :: Software Development :: Build Tools
Classifier: License :: OSI Approved :: MIT License
Classifier: Programming Language :: Python :: 3
License-File: LICENSE.txt
